file_translate/__init__.py
file_translate/config.json
file_translate/translate.py
file_translate-0.0.3.dist-info/DESCRIPTION.rst
file_translate-0.0.3.dist-info/entry_points.txt
file_translate-0.0.3.dist-info/METADATA
file_translate-0.0.3.dist-info/metadata.json
file_translate-0.0.3.dist-info/RECORD
file_translate-0.0.3.dist-info/top_level.txt
file_translate-0.0.3.dist-info/WHEEL
