Metadata-Version: 2.0
Name: file-translate
Version: 0.0.3
Summary: Utility to translate the contents of a file by running a set of regular expressions over it.
Home-page: UNKNOWN
Author: Digicat
Author-email: UNKNOWN
License: UNKNOWN
Platform: UNKNOWN
